itk/TextureFeaturesPython.py
itk/_TextureFeaturesPython.pyd
itk/__init_texturefeatures__.py
itk/itkCoocurrenceTextureFeaturesImageFilterPython.py
itk/itkRunLengthTextureFeaturesImageFilterPython.py
itk/Configuration/TextureFeaturesConfig.py
itk/Configuration/TextureFeatures_snake_case.py
itk_texturefeatures-4.0.1.dist-info/licenses/LICENSE
itk_texturefeatures.libs/msvcp140.dll
itk_texturefeatures.libs/tbb12.dll
itk_texturefeatures-4.0.1.dist-info/DELVEWHEEL
itk_texturefeatures-4.0.1.dist-info/METADATA
itk_texturefeatures-4.0.1.dist-info/WHEEL
itk_texturefeatures-4.0.1.dist-info/RECORD
